vitag/__init__.py
vitag/cli.py
vitag/core.py
vitag-1.2.0.dist-info/licenses/LICENSE
vitag-1.2.0.dist-info/METADATA
vitag-1.2.0.dist-info/WHEEL
vitag-1.2.0.dist-info/entry_points.txt
vitag-1.2.0.dist-info/top_level.txt
vitag-1.2.0.dist-info/RECORD
