Metadata-Version: 2.4
Name: vitag
Version: 1.2.0
Summary: Tag music files using your $EDITOR
Author: Tx270
License-Expression: MIT
Project-URL: Homepage, https://github.com/Tx270/vitag
Keywords: audio,music,cli,metadata,id3
Classifier: Intended Audience :: End Users/Desktop
Classifier: Topic :: Multimedia :: Sound/Audio
Classifier: Programming Language :: Python :: 3
Classifier: Programming Language :: Python
Classifier: Operating System :: OS Independent
Classifier: Environment :: Console
Requires-Python: >=3.10
License-File: LICENSE
Requires-Dist: mutagen>=1.46.0
Requires-Dist: typer>=0.9.0
Requires-Dist: rich>=13.0.0
Provides-Extra: dev
Requires-Dist: pytest; extra == "dev"
Dynamic: license-file
